{
  "PK_USUARIO": 1,
  "FK_PERFIL": 1,
  "FK_EMPRESA": 25,
  "FK_TIPO_DOCUMENTO": 1,
  "FK_ESTADO": 1,
  "HABEAS_DATA": 1,
  "CEDULA": "1111111111",
  "NOMBRE": "Administrador",
  "APELLIDO": "Registel",
  "EMAIL": "diddier.matta.registel@gmail.com",
  "LOGIN": "adminregistel",
  "MOVIL": "3104443440",
  "CONTRASENA": "8e42199beeaadd8f27bb6288f0eeef92230e272020088fee78aee57fdd4ed941",
  "ESTADO": 1,
  "MODIFICACION_LOCAL": 1,
  "PK_UNICA": "o9ikli86yt5r4dedf6h",
  "TIPO": 1,
  "TOKEN": "3663339761623",
  "EXPIRE_TOKEN": 1695913633646,
  "__atributos__": {
    "MODIFICACION": { "FECHA": "2023-10-27T05:47:04.741Z", "CONTADOR": 36 },
    "FECHA_CREACION": "2023-10-27T04:51:09.989Z"
  }
}
