{"PK_USUARIO":243,"FK_PERFIL":35,"FK_TIPO_DOCUMENTO":1,"FK_ESTADO":1,"CEDULA":"9762543","NOMBRE":"HECTOR JAIME","APELLIDO":"ALVAREZ BERMUNEZ","EMAIL":"diddier.matta@registelcolombia.com","LOGIN":"hjalvarez","MOVIL":"3154125418","CONTRASENA":"bfda1d36dafd5f0125071552036616db8edc2634b139db41839ec16601509efb","ESTADO":1,"ESTADO_CONEXION":1,"MODIFICACION_LOCAL":1,"TIPO":1,"EMPRESAS_ACCESO":[{"NOMBRE_SERVICIO":"Cooperativa","dominio":"cooperativa.regisdataweb.com","ID":25}],"__atributos__":{"SET":{"FECHA_MODIFICACION":"2023-10-27T20:55:12.903Z","CONTADOR":1},"FECHA_CREACION":"2023-10-27T20:55:12.903Z"}}