{"cursor":{"año":2023,"mes":11,"dia":28,"time":1701190203904,"file":"2023/11/28/1701190203904"},"antecesor":{"año":2023,"mes":11,"dia":28,"time":1701190066468,"file":"2023/11/28/1701190066468"},"notificacion":{"titulo":"Nombre de usuario","mensaje":"Se ha cambiado \"Nombre\" de usuario","tipo":"info","icono":"fas fa-user-edit","swal":{"title":"Nombre de usuario","parametros":{"inicial":"Alexmacias","final":"Alexmacias2","fecha":"2023-11-28 11:50:03","modificador":{"PK":2}},"html":"ha cambiado de <b>Alexmacias</b> a <b>Alexmacias2</b><br><br>2023-11-28 11:50:03<br><br><div class=ta-right>Por: alexmacias</div>"}},"ejecutor":{"PK":2},"sucesor":{"año":2023,"mes":11,"dia":28,"time":1701190265784,"file":"2023/11/28/1701190265784"}}